<?xml version="1.0" encoding="utf-8"?>
<odoo>
    <data>
        <record id="fulfill_shelf_type" model="ir.ui.view">
            <field name="name">fulfill_shelf_type</field>
            <field name="model">fulfill.shelf.type</field>
            <field name="arch" type="xml">
                <tree string="Shelf Type" editable="bottom">
                    <field name="id"/>
                    <field name="shelf_type_name" required="1"/>
                </tree>
            </field>
        </record>
        <record id="crosify_menu_fulfill_shelf_type_action"
            model="ir.actions.act_window">
            <field name="name">Shelf Type</field>
            <field name="res_model">fulfill.shelf.type</field>
            <field name="view_mode">tree,form</field>
        </record>
        <menuitem id="crosify_menu_fulfill_shelf_type" name="Shelf Type"
            parent="sale.menu_sales_config"
            action="crosify_menu_fulfill_shelf_type_action"
            sequence="23" />
    </data>
</odoo>